{
  "Ads": [
    {
       "select_main_ads": "ADMOB",
      "select_backup_ads":"APPLOVIN-M",
      "main_ads_banner": "ca-app-pub-2631643370199907/7770488939",
      "main_ads_intertitial":"ca-app-pub-2631643370199907/2549951842",
      "main_ads_natives":"ca-app-pub-2631643370199907/9255570776",
      "backup_ads_natives":"11e1e8a81672e84c",
      "backup_ads_banner":"6c9827f8f0d1bf65",
      "backup_ads_intertitial":"22846ba51ab39e9f",
      "open_ads_admob":"",
      "open_ads_alien":"",
      "switch_open_ads":"1",
      "switch_banner_natives_ads":"",
      "on_off_native_listview":"1",
      "interval_intertitial": 3,
      "initialize_sdk":"",
      "initialize_sdk_backup_ads":"",
      "high_paying_keyword_1": "",
      "high_paying_keyword_2": "",
      "high_paying_keyword_3": "",
      "high_paying_keyword_4": "",
      "high_paying_keyword_5": "",
      "status_app": "0",
      "link_redirect": "https://"

    }
  ],
  "Categories": [
    {
      "name_category": "1",
      "wallpaper_url": "https://i.pinimg.com/564x/45/60/11/456011ce68bcaebae1aeb31a571d0fbd.jpg"
    }
  ],
  "Wallpaper": [
    {
      "id": 1,
      "name_category": "1",
      "wallpaper_name": "Shinobu Kochou 1",
      "wallpaper_type": "IMAGE",
      "wallpaper_url": "https://i.pinimg.com/736x/76/ee/e9/76eee9ba6452a1193de810fc0e85f305.jpg"
    },
	{
      "id": 2,
      "name_category": "1",
      "wallpaper_name": "Shinobu Kochou 2",
      "wallpaper_type": "IMAGE",
      "wallpaper_url": "https://i.pinimg.com/564x/c4/26/c1/c426c17efad9a4a50ac5b8e23aa241d9.jpg"
    },
	{
      "id": 3,
      "name_category": "1",
      "wallpaper_name": "Shinobu Kochou 3",
      "wallpaper_type": "IMAGE",
      "wallpaper_url": "https://i.pinimg.com/564x/db/52/e6/db52e63ad1a921bb06247c50ef46374d.jpg"
    },
	{
      "id": 4,
      "name_category": "1",
      "wallpaper_name": "Shinobu Kochou 4",
      "wallpaper_type": "IMAGE",
      "wallpaper_url": "https://i.pinimg.com/736x/67/d4/1b/67d41b117a2579ed581a8a973defa0eb.jpg"
    },
	{
      "id": 5,
      "name_category": "1",
      "wallpaper_name": "Shinobu Kochou 5",
      "wallpaper_type": "IMAGE",
      "wallpaper_url": "https://i.pinimg.com/564x/42/b1/51/42b151d329eb0ae510526939ef3a1767.jpg"
    },
	{
      "id": 6,
      "name_category": "1",
      "wallpaper_name": "Shinobu Kochou 6",
      "wallpaper_type": "IMAGE",
      "wallpaper_url": "https://i.pinimg.com/564x/0a/4a/10/0a4a106fa6b08ad13a612c96af879169.jpg"
    },
	{
      "id": 7,
      "name_category": "1",
      "wallpaper_name": "Shinobu Kochou 7",
      "wallpaper_type": "IMAGE",
      "wallpaper_url": "https://i.pinimg.com/564x/56/8c/c8/568cc8c375438097dbe33f597f96bb2c.jpg"
    },
	{
      "id": 8,
      "name_category": "1",
      "wallpaper_name": "Shinobu Kochou 8",
      "wallpaper_type": "IMAGE",
      "wallpaper_url": "https://i.pinimg.com/564x/f7/28/18/f72818f9a8b2407d921d8f0dacbc2871.jpg"
    },
	{
      "id": 9,
      "name_category": "1",
      "wallpaper_name": "Shinobu Kochou 9",
      "wallpaper_type": "IMAGE",
      "wallpaper_url": "https://i.pinimg.com/564x/7f/c6/57/7fc657475119891247a43551d0ed4a38.jpg"
    },
	{
      "id": 10,
      "name_category": "1",
      "wallpaper_name": "Shinobu Kochou 10",
      "wallpaper_type": "IMAGE",
      "wallpaper_url": "https://i.pinimg.com/564x/ba/84/c7/ba84c7b7f00141b41293c62d033bc6ce.jpg"
    },
	{
      "id": 11,
      "name_category": "1",
      "wallpaper_name": "Shinobu Kochou 11",
      "wallpaper_type": "IMAGE",
      "wallpaper_url": "https://i.pinimg.com/564x/42/59/e5/4259e50e0e6d9c8b1156c30acfb1b256.jpg"
    },
	{
      "id": 12,
      "name_category": "1",
      "wallpaper_name": "Shinobu Kochou 12",
      "wallpaper_type": "IMAGE",
      "wallpaper_url": "https://i.pinimg.com/564x/26/f3/f1/26f3f10676f1c2e905c3e3487e269472.jpg"
    },
	{
      "id": 13,
      "name_category": "1",
      "wallpaper_name": "Shinobu Kochou 13",
      "wallpaper_type": "IMAGE",
      "wallpaper_url": "https://i.pinimg.com/564x/45/60/11/456011ce68bcaebae1aeb31a571d0fbd.jpg"
    },
	{
      "id": 14,
      "name_category": "1",
      "wallpaper_name": "Shinobu Kochou 14",
      "wallpaper_type": "IMAGE",
      "wallpaper_url": "https://i.pinimg.com/564x/94/0d/cd/940dcdd73fa75b7c5a58dd123d34f30c.jpg"
    },
	{
      "id": 15,
      "name_category": "1",
      "wallpaper_name": "Shinobu Kochou 15",
      "wallpaper_type": "IMAGE",
      "wallpaper_url": "https://i.pinimg.com/564x/67/b9/40/67b9405f79e6231cb09578c63b8725a4.jpg"
    },
	{
      "id": 16,
      "name_category": "1",
      "wallpaper_name": "Shinobu Kochou 16",
      "wallpaper_type": "IMAGE",
      "wallpaper_url": "https://i.pinimg.com/564x/3a/af/42/3aaf42d3fb10a12012718fafde0a2cd6.jpg"
    },
	{
      "id": 17,
      "name_category": "1",
      "wallpaper_name": "Shinobu Kochou 17",
      "wallpaper_type": "IMAGE",
      "wallpaper_url": "https://i.pinimg.com/564x/2f/e1/8a/2fe18a3a4fc4b4ada8231d9165aadff0.jpg"
    },
	{
      "id": 18,
      "name_category": "1",
      "wallpaper_name": "Shinobu Kochou 18",
      "wallpaper_type": "IMAGE",
      "wallpaper_url": "https://i.pinimg.com/564x/0a/b0/8d/0ab08dd3baba7f589ff46ef9e94bd3f1.jpg"
    },
	{
      "id": 19,
      "name_category": "1",
      "wallpaper_name": "Shinobu Kochou 19",
      "wallpaper_type": "IMAGE",
      "wallpaper_url": "https://i.pinimg.com/564x/75/27/51/752751e5afec7905b9fb8221a87dcaea.jpg"
    },
	{
      "id": 20,
      "name_category": "1",
      "wallpaper_name": "Shinobu Kochou 20",
      "wallpaper_type": "IMAGE",
      "wallpaper_url": "https://i.pinimg.com/564x/74/32/cd/7432cd4a6d81808c4cd57eb5e956848a.jpg"
    },
	{
      "id": 21,
      "name_category": "1",
      "wallpaper_name": "Shinobu Kochou 21",
      "wallpaper_type": "IMAGE",
      "wallpaper_url": "https://i.pinimg.com/564x/17/74/78/1774785bc91eeb67161009897b1eaa09.jpg"
    },
	{
      "id": 22,
      "name_category": "1",
      "wallpaper_name": "Shinobu Kochou 22",
      "wallpaper_type": "IMAGE",
      "wallpaper_url": "https://i.pinimg.com/564x/3e/4a/3b/3e4a3b65d6018652eb7d733e66cf851a.jpg"
    },
	{
      "id": 23,
      "name_category": "1",
      "wallpaper_name": "Shinobu Kochou 23",
      "wallpaper_type": "IMAGE",
      "wallpaper_url": "https://i.pinimg.com/564x/99/a8/ac/99a8ac98f315cef09ce06894f7bcbe26.jpg"
    },
	{
      "id": 24,
      "name_category": "1",
      "wallpaper_name": "Shinobu Kochou 24",
      "wallpaper_type": "IMAGE",
      "wallpaper_url": "https://i.pinimg.com/564x/d5/ba/e7/d5bae705bbb538a26d953540b340d9dd.jpg"
    },
	{
      "id": 25,
      "name_category": "1",
      "wallpaper_name": "Shinobu Kochou 25",
      "wallpaper_type": "IMAGE",
      "wallpaper_url": "https://i.pinimg.com/564x/81/cb/c0/81cbc04a23ff9585adcfd5ae44b33cd1.jpg"
    },
	{
      "id": 26,
      "name_category": "1",
      "wallpaper_name": "Shinobu Kochou 26",
      "wallpaper_type": "IMAGE",
      "wallpaper_url": "https://i.pinimg.com/564x/26/15/60/261560d31f27f11621d2a3d788696cba.jpg"
    },
	{
      "id": 27,
      "name_category": "1",
      "wallpaper_name": "Shinobu Kochou 27",
      "wallpaper_type": "IMAGE",
      "wallpaper_url": "https://i.pinimg.com/564x/a4/ec/f3/a4ecf35c9bb8ffd64d519ac6894558a6.jpg"
    },
	{
      "id": 28,
      "name_category": "1",
      "wallpaper_name": "Shinobu Kochou 28",
      "wallpaper_type": "IMAGE",
      "wallpaper_url": "https://i.pinimg.com/564x/7b/e9/29/7be9299b9e11c16e00214e7a7dd7362a.jpg"
    },
	{
      "id": 29,
      "name_category": "1",
      "wallpaper_name": "Shinobu Kochou 29",
      "wallpaper_type": "IMAGE",
      "wallpaper_url": "https://i.pinimg.com/564x/58/50/d8/5850d8806ab4c86cd99c01689fb0756c.jpg"
    },
	{
      "id": 30,
      "name_category": "1",
      "wallpaper_name": "Shinobu Kochou 30",
      "wallpaper_type": "IMAGE",
      "wallpaper_url": "https://i.pinimg.com/564x/20/31/78/203178ac656b9b6b21dfa9cbffd80c88.jpg"
    },
	{
      "id": 31,
      "name_category": "1",
      "wallpaper_name": "Shinobu Kochou 31",
      "wallpaper_type": "IMAGE",
      "wallpaper_url": "https://i.pinimg.com/564x/3f/40/35/3f4035a2d62d58daf8d20924dceb813e.jpg"
    },
	{
      "id": 32,
      "name_category": "1",
      "wallpaper_name": "Shinobu Kochou 32",
      "wallpaper_type": "IMAGE",
      "wallpaper_url": "https://i.pinimg.com/564x/de/20/70/de20702b65fe60c31b1deaab136aae1e.jpg"
    },
	{
      "id": 33,
      "name_category": "1",
      "wallpaper_name": "Shinobu Kochou 33",
      "wallpaper_type": "IMAGE",
      "wallpaper_url": "https://i.pinimg.com/564x/5f/30/b4/5f30b4e854969c7f4de4b48907d85cd1.jpg"
    },
	{
      "id": 34,
      "name_category": "1",
      "wallpaper_name": "Shinobu Kochou 34",
      "wallpaper_type": "IMAGE",
      "wallpaper_url": "https://i.pinimg.com/564x/fa/d3/37/fad33767d4ed12feb0bde46ca9d2087e.jpg"
    },
	{
      "id": 35,
      "name_category": "1",
      "wallpaper_name": "Shinobu Kochou 35",
      "wallpaper_type": "IMAGE",
      "wallpaper_url": "https://i.pinimg.com/564x/ad/4a/85/ad4a85c37aa2bfeab9851c94f0bc8fb4.jpg"
    },
	{
      "id": 36,
      "name_category": "1",
      "wallpaper_name": "Shinobu Kochou 36",
      "wallpaper_type": "IMAGE",
      "wallpaper_url": "https://i.pinimg.com/564x/9d/92/0f/9d920f6c701eab7fcee7355b0127054e.jpg"
    },
	{
      "id": 37,
      "name_category": "1",
      "wallpaper_name": "Shinobu Kochou 37",
      "wallpaper_type": "IMAGE",
      "wallpaper_url": "https://i.pinimg.com/564x/58/2b/70/582b70e4c1bed2621c256a99caa316bb.jpg"
    },
	{
      "id": 38,
      "name_category": "1",
      "wallpaper_name": "Shinobu Kochou 38",
      "wallpaper_type": "IMAGE",
      "wallpaper_url": "https://i.pinimg.com/564x/29/bd/87/29bd87d062ddef775c545e1887fb4ca6.jpg"
    },
	{
      "id": 39,
      "name_category": "1",
      "wallpaper_name": "Shinobu Kochou 39",
      "wallpaper_type": "IMAGE",
      "wallpaper_url": "https://i.pinimg.com/564x/2e/b6/94/2eb694d8bf5415403027a104e7def667.jpg"
    },
	{
      "id": 40,
      "name_category": "1",
      "wallpaper_name": "Shinobu Kochou 40",
      "wallpaper_type": "IMAGE",
      "wallpaper_url": "https://i.pinimg.com/564x/59/88/1e/59881e7f381bb7b58e6b7b3bb7fc1766.jpg"
    },
	{
      "id": 41,
      "name_category": "1",
      "wallpaper_name": "Shinobu Kochou 41",
      "wallpaper_type": "IMAGE",
      "wallpaper_url": "https://i.pinimg.com/736x/7b/40/3b/7b403b3291e2241dab1a5f18e4e13fbe.jpg"
    },
	{
      "id": 42,
      "name_category": "1",
      "wallpaper_name": "Shinobu Kochou 42",
      "wallpaper_type": "IMAGE",
      "wallpaper_url": "https://i.pinimg.com/564x/d1/f7/76/d1f7762a20ba958bcf9cf9050e8a8c2a.jpg"
    },
	{
      "id": 43,
      "name_category": "1",
      "wallpaper_name": "Shinobu Kochou 43",
      "wallpaper_type": "IMAGE",
      "wallpaper_url": "https://i.pinimg.com/564x/0d/37/d5/0d37d5b057dfe16e176207d8eafcd373.jpg"
    },
	{
      "id": 44,
      "name_category": "1",
      "wallpaper_name": "Shinobu Kochou 44",
      "wallpaper_type": "IMAGE",
      "wallpaper_url": "https://i.pinimg.com/564x/fe/f3/9b/fef39bb7e5c95958c6b35a9caac1a838.jpg"
    },
	{
      "id": 45,
      "name_category": "1",
      "wallpaper_name": "Shinobu Kochou 45",
      "wallpaper_type": "IMAGE",
      "wallpaper_url": "https://i.pinimg.com/564x/b1/01/ab/b101ab5d6380bf89cb68dbb41e73fea1.jpg"
    },
	{
      "id": 46,
      "name_category": "1",
      "wallpaper_name": "Shinobu Kochou 46",
      "wallpaper_type": "IMAGE",
      "wallpaper_url": "https://i.pinimg.com/564x/02/58/37/0258376e0ad2c332b62a294fd5467a78.jpg"
    },
	{
      "id": 47,
      "name_category": "1",
      "wallpaper_name": "Shinobu Kochou 47",
      "wallpaper_type": "IMAGE",
      "wallpaper_url": "https://i.pinimg.com/564x/e8/f3/0a/e8f30a14a3327972548f4bc6050332d3.jpg"
    },
	{
      "id": 48,
      "name_category": "1",
      "wallpaper_name": "Shinobu Kochou 48",
      "wallpaper_type": "IMAGE",
      "wallpaper_url": "https://i.pinimg.com/564x/d1/ee/7d/d1ee7d021c86ba15210897a98d84260a.jpg"
    },
	{
      "id": 49,
      "name_category": "1",
      "wallpaper_name": "Shinobu Kochou 49",
      "wallpaper_type": "IMAGE",
      "wallpaper_url": "https://i.pinimg.com/564x/99/6b/d3/996bd368ab0963e96ec7bdff4fe50392.jpg"
    },
	{
      "id": 50,
      "name_category": "1",
      "wallpaper_name": "Shinobu Kochou 50",
      "wallpaper_type": "IMAGE",
      "wallpaper_url": "https://i.pinimg.com/564x/56/8c/c8/568cc8c375438097dbe33f597f96bb2c.jpg"
    },
	{
      "id": 51,
      "name_category": "1",
      "wallpaper_name": "Shinobu Kochou 51",
      "wallpaper_type": "IMAGE",
      "wallpaper_url": "https://i.pinimg.com/564x/09/64/3c/09643c56015738768dc403309d5569f0.jpg"
    },
	{
      "id": 52,
      "name_category": "1",
      "wallpaper_name": "Shinobu Kochou 52",
      "wallpaper_type": "IMAGE",
      "wallpaper_url": "https://i.pinimg.com/564x/59/11/4d/59114dba4db97faec7498d87eccc277c.jpg"
    },
	{
      "id": 53,
      "name_category": "1",
      "wallpaper_name": "Shinobu Kochou 53",
      "wallpaper_type": "IMAGE",
      "wallpaper_url": "https://i.pinimg.com/564x/f8/68/f4/f868f4779cccc74f10e311cb3468182b.jpg"
    },
	{
      "id": 54,
      "name_category": "1",
      "wallpaper_name": "Shinobu Kochou 54",
      "wallpaper_type": "IMAGE",
      "wallpaper_url": "https://i.pinimg.com/564x/72/16/85/7216856bf01749ae5819cf90d226c276.jpg"
    },
	{
      "id": 55,
      "name_category": "1",
      "wallpaper_name": "Shinobu Kochou 55",
      "wallpaper_type": "IMAGE",
      "wallpaper_url": "https://i.pinimg.com/564x/c8/a9/52/c8a9526644c3a8ed5001622596a5cf08.jpg"
    },
	{
      "id": 56,
      "name_category": "1",
      "wallpaper_name": "Shinobu Kochou 56",
      "wallpaper_type": "IMAGE",
      "wallpaper_url": "https://i.pinimg.com/564x/61/0e/87/610e87e077df77996eb1fa7d96d233ba.jpg"
    },
	{
      "id": 57,
      "name_category": "1",
      "wallpaper_name": "Shinobu Kochou 57",
      "wallpaper_type": "IMAGE",
      "wallpaper_url": "https://i.pinimg.com/564x/10/9d/b5/109db5468a7fb71756feea7071b59f82.jpg"
    },
	{
      "id": 58,
      "name_category": "1",
      "wallpaper_name": "Shinobu Kochou 58",
      "wallpaper_type": "IMAGE",
      "wallpaper_url": "https://i.pinimg.com/564x/c2/cd/fa/c2cdfa0dd47ed68d7e7e8e5d8382f53c.jpg"
    },
	{
      "id": 59,
      "name_category": "1",
      "wallpaper_name": "Shinobu Kochou 59",
      "wallpaper_type": "IMAGE",
      "wallpaper_url": "https://i.pinimg.com/564x/d0/31/be/d031bedcdf15eb05bbb2158aabcbd566.jpg"
    },
	{
      "id": 60,
      "name_category": "1",
      "wallpaper_name": "Shinobu Kochou 60",
      "wallpaper_type": "IMAGE",
      "wallpaper_url": "https://i.pinimg.com/564x/47/51/7c/47517c17fb538da1f689813e02b2a9fc.jpg"
    },
	{
      "id": 61,
      "name_category": "1",
      "wallpaper_name": "Shinobu Kochou 61",
      "wallpaper_type": "IMAGE",
      "wallpaper_url": "https://i.pinimg.com/564x/88/20/74/882074d488f8acd461932cc3c686ad6e.jpg"
    },
	{
      "id": 62,
      "name_category": "1",
      "wallpaper_name": "Shinobu Kochou 62",
      "wallpaper_type": "IMAGE",
      "wallpaper_url": "https://i.pinimg.com/564x/ba/84/c7/ba84c7b7f00141b41293c62d033bc6ce.jpg"
    },
	{
      "id": 63,
      "name_category": "1",
      "wallpaper_name": "Shinobu Kochou 63",
      "wallpaper_type": "IMAGE",
      "wallpaper_url": "https://i.pinimg.com/564x/08/30/f3/0830f3a4bd20c417962f8c08a874f64c.jpg"
    },
	{
      "id": 64,
      "name_category": "1",
      "wallpaper_name": "Shinobu Kochou 64",
      "wallpaper_type": "IMAGE",
      "wallpaper_url": "https://i.pinimg.com/564x/38/58/b0/3858b09edfc4e9322d02e740a2f7c5d6.jpg"
    },
	{
      "id": 65,
      "name_category": "1",
      "wallpaper_name": "Shinobu Kochou 65",
      "wallpaper_type": "IMAGE",
      "wallpaper_url": "https://i.pinimg.com/564x/02/92/e3/0292e36542ff99e22a1575b025558cc4.jpg"
    },
	{
      "id": 66,
      "name_category": "1",
      "wallpaper_name": "Shinobu Kochou 66",
      "wallpaper_type": "IMAGE",
      "wallpaper_url": "https://i.pinimg.com/564x/5c/43/4f/5c434f6793b4a723106944e6f5cc4750.jpg"
    },
	{
      "id": 67,
      "name_category": "1",
      "wallpaper_name": "Shinobu Kochou 67",
      "wallpaper_type": "IMAGE",
      "wallpaper_url": "https://i.pinimg.com/564x/f7/21/1b/f7211be7a977a889f9265454c8695ba7.jpg"
    },
	{
      "id": 68,
      "name_category": "1",
      "wallpaper_name": "Shinobu Kochou 68",
      "wallpaper_type": "IMAGE",
      "wallpaper_url": "https://i.pinimg.com/564x/88/72/c6/8872c65ab75c39985ead0b6711f6932d.jpg"
    },
	{
      "id": 69,
      "name_category": "1",
      "wallpaper_name": "Shinobu Kochou 69",
      "wallpaper_type": "IMAGE",
      "wallpaper_url": "https://i.pinimg.com/564x/30/ee/3b/30ee3b28d8d7788cea85e4acfe37816b.jpg"
    },
	{
      "id": 70,
      "name_category": "1",
      "wallpaper_name": "Shinobu Kochou 70",
      "wallpaper_type": "IMAGE",
      "wallpaper_url": "https://i.pinimg.com/564x/50/a6/d5/50a6d577f0406c4ab6746e76cc5b347a.jpg"
    },
	{
      "id": 71,
      "name_category": "1",
      "wallpaper_name": "Shinobu Kochou 71",
      "wallpaper_type": "IMAGE",
      "wallpaper_url": "https://i.pinimg.com/564x/10/6d/67/106d679653525816fb4a33b1b3d33c3f.jpg"
    },
	{
      "id": 72,
      "name_category": "1",
      "wallpaper_name": "Shinobu Kochou 72",
      "wallpaper_type": "IMAGE",
      "wallpaper_url": "https://i.pinimg.com/564x/56/8c/c8/568cc8c375438097dbe33f597f96bb2c.jpg"
    },
	{
      "id": 73,
      "name_category": "1",
      "wallpaper_name": "Shinobu Kochou 73",
      "wallpaper_type": "IMAGE",
      "wallpaper_url": "https://i.pinimg.com/564x/65/a7/ba/65a7ba29def287faab2955bf9968d648.jpg"
    },
	{
      "id": 74,
      "name_category": "1",
      "wallpaper_name": "Shinobu Kochou 74",
      "wallpaper_type": "IMAGE",
      "wallpaper_url": "https://i.pinimg.com/564x/81/c8/25/81c82592dae52b7cb8ce9c2d253c6558.jpg"
    },
	{
      "id": 75,
      "name_category": "1",
      "wallpaper_name": "Shinobu Kochou 75",
      "wallpaper_type": "IMAGE",
      "wallpaper_url": "https://i.pinimg.com/564x/e1/8f/16/e18f16f904020585217efeae4becaf40.jpg"
    },
	{
      "id": 76,
      "name_category": "1",
      "wallpaper_name": "Shinobu Kochou 76",
      "wallpaper_type": "IMAGE",
      "wallpaper_url": "https://i.pinimg.com/564x/6a/fa/46/6afa4657bd315d005e6d015f3737e647.jpg"
    },
	{
      "id": 77,
      "name_category": "1",
      "wallpaper_name": "Shinobu Kochou 77",
      "wallpaper_type": "IMAGE",
      "wallpaper_url": "https://i.pinimg.com/564x/34/c7/ee/34c7ee331cf55c8d6a25445621e1f2aa.jpg"
    },
	{
      "id": 78,
      "name_category": "1",
      "wallpaper_name": "Shinobu Kochou 78",
      "wallpaper_type": "IMAGE",
      "wallpaper_url": "https://i.pinimg.com/564x/24/64/57/246457ab9fc32ee6ad02c8af4f01401a.jpg"
    },
	{
      "id": 79,
      "name_category": "1",
      "wallpaper_name": "Shinobu Kochou 79",
      "wallpaper_type": "IMAGE",
      "wallpaper_url": "https://i.pinimg.com/564x/c1/65/b3/c165b3944ce8474ece426912e05e1f66.jpg"
    },
	{
      "id": 80,
      "name_category": "1",
      "wallpaper_name": "Shinobu Kochou 80",
      "wallpaper_type": "IMAGE",
      "wallpaper_url": "https://i.pinimg.com/564x/63/c7/d0/63c7d041d267a5b4b1b7065f37e24492.jpg"
    },
	{
      "id": 81,
      "name_category": "1",
      "wallpaper_name": "Shinobu Kochou 81",
      "wallpaper_type": "IMAGE",
      "wallpaper_url": "https://i.pinimg.com/564x/98/a6/36/98a63681ccb58546b749e1ddbe7e4ede.jpg"
    },
	{
      "id": 82,
      "name_category": "1",
      "wallpaper_name": "Shinobu Kochou 82",
      "wallpaper_type": "IMAGE",
      "wallpaper_url": "https://i.pinimg.com/564x/5c/30/b0/5c30b0e8c9e6d37bc18fed74a4f6ba56.jpg"
    },
	{
      "id": 83,
      "name_category": "1",
      "wallpaper_name": "Shinobu Kochou 83",
      "wallpaper_type": "IMAGE",
      "wallpaper_url": "https://i.pinimg.com/564x/93/5d/2b/935d2b76257b615602b65404de8c7037.jpg"
    },
	{
      "id": 84,
      "name_category": "1",
      "wallpaper_name": "Shinobu Kochou 84",
      "wallpaper_type": "IMAGE",
      "wallpaper_url": "https://i.pinimg.com/564x/e2/26/3d/e2263ddb9d85b0c642883a6d188b3d27.jpg"
    },
	{
      "id": 85,
      "name_category": "1",
      "wallpaper_name": "Shinobu Kochou 85",
      "wallpaper_type": "IMAGE",
      "wallpaper_url": "https://i.pinimg.com/564x/51/56/93/515693dc0f29c69a5c3b2dea6d0c16b4.jpg"
    },
	{
      "id": 86,
      "name_category": "1",
      "wallpaper_name": "Shinobu Kochou 86",
      "wallpaper_type": "IMAGE",
      "wallpaper_url": "https://i.pinimg.com/564x/93/5d/2b/935d2b76257b615602b65404de8c7037.jpg"
    },
	{
      "id": 87,
      "name_category": "1",
      "wallpaper_name": "Shinobu Kochou 87",
      "wallpaper_type": "IMAGE",
      "wallpaper_url": "https://i.pinimg.com/564x/1e/bf/b0/1ebfb08e0170ab366d2955690431f9b3.jpg"
    },
	{
      "id": 88,
      "name_category": "1",
      "wallpaper_name": "Shinobu Kochou 88",
      "wallpaper_type": "IMAGE",
      "wallpaper_url": "https://i.pinimg.com/564x/48/ef/fc/48effc22bf58942d504e52557060f079.jpg"
    },
	{
      "id": 89,
      "name_category": "1",
      "wallpaper_name": "Shinobu Kochou 89",
      "wallpaper_type": "IMAGE",
      "wallpaper_url": "https://i.pinimg.com/564x/80/da/36/80da365ee10af4d46f9bfd6167e6a026.jpg"
    },
	{
      "id": 90,
      "name_category": "1",
      "wallpaper_name": "Shinobu Kochou 90",
      "wallpaper_type": "IMAGE",
      "wallpaper_url": "https://i.pinimg.com/564x/16/98/61/169861fb72db3e2671edb5f2d57499de.jpg"
    },
	{
      "id": 91,
      "name_category": "1",
      "wallpaper_name": "Shinobu Kochou 91",
      "wallpaper_type": "IMAGE",
      "wallpaper_url": "https://i.pinimg.com/564x/f6/72/df/f672df25244e01791bca6d439eb46b93.jpg"
    },
	{
      "id": 92,
      "name_category": "1",
      "wallpaper_name": "Shinobu Kochou 92",
      "wallpaper_type": "IMAGE",
      "wallpaper_url": "https://i.pinimg.com/564x/05/13/d4/0513d44a882beffe056a069d63fb0a42.jpg"
    },
	{
      "id": 93,
      "name_category": "1",
      "wallpaper_name": "Shinobu Kochou 93",
      "wallpaper_type": "IMAGE",
      "wallpaper_url": "https://i.pinimg.com/564x/fe/98/4b/fe984b7e88a488bd932d6c72f3042588.jpg"
    },
	{
      "id": 94,
      "name_category": "1",
      "wallpaper_name": "Shinobu Kochou 94",
      "wallpaper_type": "IMAGE",
      "wallpaper_url": "https://i.pinimg.com/564x/83/b8/42/83b842faf401567fe87b9d1771828d8d.jpg"
    },
	{
      "id": 95,
      "name_category": "1",
      "wallpaper_name": "Shinobu Kochou 95",
      "wallpaper_type": "IMAGE",
      "wallpaper_url": "https://i.pinimg.com/564x/85/26/e7/8526e7577d04b960d5b29508bf6bd7d6.jpg"
    },
	{
      "id": 96,
      "name_category": "1",
      "wallpaper_name": "Shinobu Kochou 96",
      "wallpaper_type": "IMAGE",
      "wallpaper_url": "https://i.pinimg.com/564x/55/c6/71/55c671a8167c10b2fe6986e0b9dd545b.jpg"
    },
	{
      "id": 97,
      "name_category": "1",
      "wallpaper_name": "Shinobu Kochou 97",
      "wallpaper_type": "IMAGE",
      "wallpaper_url": "https://i.pinimg.com/564x/bd/ec/56/bdec5628f6b9ede45a547343d93ae632.jpg"
    },
	{
      "id": 98,
      "name_category": "1",
      "wallpaper_name": "Shinobu Kochou 98",
      "wallpaper_type": "IMAGE",
      "wallpaper_url": "https://i.pinimg.com/564x/e4/26/c9/e426c90b4270d1eeb08372590d05d797.jpg"
    },
	{
      "id": 99,
      "name_category": "1",
      "wallpaper_name": "Shinobu Kochou 99",
      "wallpaper_type": "IMAGE",
      "wallpaper_url": "https://i.pinimg.com/564x/c5/4b/f4/c54bf4ce38be1a3fcef4127b3b86f29a.jpg"
    },
	{
      "id": 100,
      "name_category": "1",
      "wallpaper_name": "Shinobu Kochou 100",
      "wallpaper_type": "IMAGE",
      "wallpaper_url": "https://i.pinimg.com/564x/35/ca/bf/35cabf37be04ce7a0fa2d90c9032f7be.jpg"
    },
	{
      "id": 101,
      "name_category": "1",
      "wallpaper_name": "Shinobu Kochou 101",
      "wallpaper_type": "IMAGE",
      "wallpaper_url": "https://i.pinimg.com/564x/de/c6/ef/dec6ef8467b95ee7c741e0d783c6ffd2.jpg"
    },
	{
      "id": 102,
      "name_category": "1",
      "wallpaper_name": "Shinobu Kochou 102",
      "wallpaper_type": "IMAGE",
      "wallpaper_url": "https://i.pinimg.com/564x/86/6c/f7/866cf72b5720e539d1714d54e5c94df9.jpg"
    },
	{
      "id": 103,
      "name_category": "1",
      "wallpaper_name": "Shinobu Kochou 103",
      "wallpaper_type": "IMAGE",
      "wallpaper_url": "https://i.pinimg.com/564x/f8/a7/d3/f8a7d308a58b68f580bbcf4027e2a278.jpg"
    },
	{
      "id": 104,
      "name_category": "1",
      "wallpaper_name": "Shinobu Kochou 104",
      "wallpaper_type": "IMAGE",
      "wallpaper_url": "https://i.pinimg.com/564x/f5/7d/df/f57ddfbfb34c85785411dd491a4f275d.jpg"
    },
	{
      "id": 105,
      "name_category": "1",
      "wallpaper_name": "Shinobu Kochou 105",
      "wallpaper_type": "IMAGE",
      "wallpaper_url": "https://i.pinimg.com/564x/fd/d1/26/fdd126814d5329cf4caa8cfbf3c9ebfc.jpg"
    },
	{
      "id": 106,
      "name_category": "1",
      "wallpaper_name": "Shinobu Kochou 106",
      "wallpaper_type": "IMAGE",
      "wallpaper_url": "https://i.pinimg.com/564x/80/85/30/8085305f8366ef1ba006214c9a16c481.jpg"
    },
	{
      "id": 107,
      "name_category": "1",
      "wallpaper_name": "Shinobu Kochou 107",
      "wallpaper_type": "IMAGE",
      "wallpaper_url": "https://i.pinimg.com/564x/41/20/9c/41209cdc8c4cbc9ef284a1237039f33f.jpg"
    },
	{
      "id": 108,
      "name_category": "1",
      "wallpaper_name": "Shinobu Kochou 108",
      "wallpaper_type": "IMAGE",
      "wallpaper_url": "https://i.pinimg.com/736x/93/b4/a5/93b4a5cc323903137c7b4f66bfcb7ae0.jpg"
    },
	{
      "id": 109,
      "name_category": "1",
      "wallpaper_name": "Shinobu Kochou 109",
      "wallpaper_type": "IMAGE",
      "wallpaper_url": "https://i.pinimg.com/564x/80/41/80/804180713d60a1bde13ca341f1413aec.jpg"
    },
	{
      "id": 110,
      "name_category": "1",
      "wallpaper_name": "Shinobu Kochou 110",
      "wallpaper_type": "IMAGE",
      "wallpaper_url": "https://i.pinimg.com/564x/ac/30/19/ac301958929df5de3e11e6610b44108f.jpg"
    }
    
  ]
}
